Metadata-Version: 2.1
Name: junopy
Version: 0.0.7
Summary: SDK Python3 para Integração com Juno API V2
Home-page: https://github.com/robertons/junopy
Author: Roberto Neves
Author-email: robertonsilva@gmail.com
License: MIT
Keywords: juno,pagamento,cartão de crédito,boleto,pix,pagamentos,transações,payment,payments,credit-card
Platform: UNKNOWN
Classifier: Development Status :: 5 - Production/Stable
Classifier: Environment :: Web Environment
Classifier: Intended Audience :: Developers
Classifier: Natural Language :: Portuguese (Brazilian)
Classifier: Operating System :: OS Independent
Classifier: License :: OSI Approved :: MIT License
Classifier: Programming Language :: Python :: 3
Classifier: Programming Language :: Python :: Implementation :: PyPy
Classifier: Topic :: Internet
Classifier: Topic :: Office/Business
Classifier: Topic :: Utilities
License-File: LICENSE
